xmipp_metadata/__init__.py
xmipp_metadata/utils.py
xmipp_metadata/image_handler/__init__.py
xmipp_metadata/image_handler/image_array.py
xmipp_metadata/image_handler/image_em.py
xmipp_metadata/image_handler/image_handler.py
xmipp_metadata/image_handler/image_mrc.py
xmipp_metadata/image_handler/image_spider.py
xmipp_metadata/metadata/__init__.py
xmipp_metadata/metadata/xmipp_metadata.py
xmipp_metadata/tests/__init__.py
xmipp_metadata/tests/test_image_handler.py
xmipp_metadata/tests/test_metadata.py
xmipp_metadata/tests/test_metadata_two_sets.py
xmipp_metadata-1.2.1.dist-info/licenses/LICENSE
xmipp_metadata-1.2.1.dist-info/METADATA
xmipp_metadata-1.2.1.dist-info/WHEEL
xmipp_metadata-1.2.1.dist-info/top_level.txt
xmipp_metadata-1.2.1.dist-info/RECORD
