Metadata-Version: 2.4
Name: xmipp_metadata
Version: 1.2.1
Summary: Package to handle Xmipp Metadata and image binary data
Home-page: https://github.com/DavidHerreros/xmipp_metadata
Author: David Herreros
Author-email: dherreros@cnb.csic.es
Keywords: xmipp scipion cryoem imageprocessing scipion-3.0
License-File: LICENSE
Requires-Dist: numpy<=1.26.4
Requires-Dist: pillow==8.4.0; python_version == "3.6"
Requires-Dist: pillow<=10.1.0; python_version >= "3.8"
Requires-Dist: pandas<=2.1.4
Requires-Dist: starfile!=0.5.0
Requires-Dist: mrcfile
Requires-Dist: emfile
Requires-Dist: emtable
Requires-Dist: scikit-image<=0.24.0
Requires-Dist: morphsnakes
Requires-Dist: joblib
Requires-Dist: pytest
Dynamic: author
Dynamic: author-email
Dynamic: description
Dynamic: description-content-type
Dynamic: home-page
Dynamic: keywords
Dynamic: license-file
Dynamic: requires-dist
Dynamic: summary
